Metadata-Version: 1.1
Name: yaochao
Version: 0.0.2
Summary: yaochao
Home-page: https://github.com/yaochao
Author: yaochao
Author-email: yaochao365@qq.com
License: MIT
Download-URL: https://github.com/yaochao/yaochao/archive/0.0.2.tar.gz
Keywords: yaochao
Platform: UNKNOWN
